ginseng/__init__.py
ginseng/data/__init__.py
ginseng/data/dataset.py
ginseng/data/io.py
ginseng/model/__init__.py
ginseng/model/nn.py
ginseng/model/predict.py
ginseng/model/state.py
ginseng/train/__init__.py
ginseng/train/augment.py
ginseng/train/logger.py
ginseng/train/opt.py
ginseng/train/trainer.py
ginseng/utils/__init__.py
ginseng/utils/hvg.py
ginseng-0.2.0.dist-info/METADATA
ginseng-0.2.0.dist-info/WHEEL
ginseng-0.2.0.dist-info/entry_points.txt
ginseng-0.2.0.dist-info/licenses/LICENSE
ginseng-0.2.0.dist-info/RECORD
