Metadata-Version: 2.4
Name: ginseng
Version: 0.2.0
Summary: Efficient and accurate annotation for single-cell sequencing data
Author-email: Tom Ouellette <touellette112@gmail.com>
License-File: LICENSE
Requires-Python: >=3.12
Requires-Dist: anndata>=0.12.2
Requires-Dist: jax>=0.7.1
Requires-Dist: jaxtyping>=0.3.2
Requires-Dist: numpy>=2.2
Requires-Dist: scipy>=1.16.1
Requires-Dist: tqdm>=4.67.1
